paramclass/__init__.py
paramclass/base.py
paramclass/common.py
paramclass/linker.py
paramclass/mask.py
paramclass-1.0.0.dist-info/METADATA
paramclass-1.0.0.dist-info/WHEEL
paramclass-1.0.0.dist-info/top_level.txt
paramclass-1.0.0.dist-info/RECORD
